xuk/__init__.py
xuk/fixed_incom/__init__.py
xuk/fixed_incom/ytm.py
xuk/options/__init__.py
xuk/options/position_builder.py
xuk/options/position_profit.py
xuk/options/pricing.py
xuk/options/strategy.py
xuk/options/utils/__init__.py
xuk/options/utils/columns.py
xuk/portfolio/__init__.py
xuk/portfolio/kelly.py
xuk/ta/__init__.py
xuk/ta/trend/__init__.py
xuk/ta/trend/dow.py
xuk/ta/trend/pct_change.py
xuk-0.1.16.dist-info/METADATA
xuk-0.1.16.dist-info/WHEEL
xuk-0.1.16.dist-info/RECORD
