Metadata-Version: 2.1
Name: xuk
Version: 0.1.16
Summary: 
Home-page: https://github.com/yghaderi/xuk
Author: Yaghoub Ghadri
Author-email: y.ghaderi@outlook.com
Requires-Python: >=3.10,<4.0
Classifier: Programming Language :: Python :: 3
Classifier: Programming Language :: Python :: 3.10
Classifier: Programming Language :: Python :: 3.11
Requires-Dist: polars (>=0.20.5,<0.21.0)
Requires-Dist: pydantic (>=2.4.2,<3.0.0)
Project-URL: Repository, https://github.com/yghaderi/xuk
